pyatus/__init__.py
pyatus/checker.py
pyatus/config.py
pyatus/converter.py
pyatus/reader.py
pyatus/utilities.py
pyatus/writer.py
Pyatus-1.0.2.dist-info/LICENSE
Pyatus-1.0.2.dist-info/METADATA
Pyatus-1.0.2.dist-info/WHEEL
Pyatus-1.0.2.dist-info/entry_points.txt
Pyatus-1.0.2.dist-info/top_level.txt
Pyatus-1.0.2.dist-info/RECORD
