Metadata-Version: 2.2
Name: Pyatus
Version: 1.0.2
Summary: Pyatus is another localization QA tool.
Home-page: https://github.com/ahanba/pyatus
Author: Ayumu Hanba
Classifier: Programming Language :: Python
Classifier: License :: OSI Approved :: MIT License
Classifier: Operating System :: OS Independent
License-File: LICENSE
Requires-Dist: pyspellchecker
Requires-Dist: openpyxl
Requires-Dist: XlsxWriter
Requires-Dist: pandas
Requires-Dist: PyYAML
Dynamic: author
Dynamic: classifier
Dynamic: description
Dynamic: description-content-type
Dynamic: home-page
Dynamic: requires-dist
Dynamic: summary
